{
  "id": "1e8c3e5f-9c6e-4dfa-8e63-a382781d8ca2",
  "prevId": "1e8c3e5f-9c6e-4dfa-8e63-a382781d8ca1",
  "version": "7",
  "dialect": "postgresql",
  "tables": {
    "public.users": {
      "name": "users",
      "schema": "",
      "columns": {
        "id": {
          "name": "id",
          "type": "serial",
          "primaryKey": true,
          "notNull": true
        },
        "name": {
          "name": "name",
          "type": "text",
          "primaryKey": false,
          "notNull": true
        },
        "email": {
          "name": "email",
          "type": "varchar(255)",
          "primaryKey": false,
          "notNull": true
        },
        "password": {
          "name": "password",
          "type": "text",
          "primaryKey": false,
          "notNull": false
        },
        "google_id": {
          "name": "google_id",
          "type": "varchar(255)",
          "primaryKey": false,
          "notNull": false
        },
        "avatar_url": {
          "name": "avatar_url",
          "type": "text",
          "primaryKey": false,
          "notNull": false
        },
        "balance": {
          "name": "balance",
          "type": "numeric(15,2)",
          "primaryKey": false,
          "notNull": false,
          "default": "'100000.00'"
        },
        "is_activated": {
          "name": "is_activated",
          "type": "boolean",
          "primaryKey": false,
          "notNull": false,
          "default": "false"
        },
        "activation_token": {
          "name": "activation_token",
          "type": "text",
          "primaryKey": false,
          "notNull": false
        },
        "created_at": {
          "name": "created_at",
          "type": "timestamp",
          "primaryKey": false,
          "notNull": false,
          "default": "now()"
        }
      },
      "indexes": {},
      "foreignKeys": {},
      "compositePrimaryKeys": {},
      "uniqueConstraints": {
        "users_email_unique": {
          "name": "users_email_unique",
          "columns": ["email"]
        }
      },
      "policies": {},
      "checkConstraints": {},
      "isRLSEnabled": false
    },
    "public.assets": {
      "name": "assets",
      "schema": "",
      "columns": {
        "id": {
          "name": "id",
          "type": "serial",
          "primaryKey": true,
          "notNull": true
        },
        "symbol": {
          "name": "symbol",
          "type": "varchar(20)",
          "primaryKey": false,
          "notNull": true
        },
        "name": {
          "name": "name",
          "type": "text",
          "primaryKey": false,
          "notNull": true
        },
        "type": {
          "name": "type",
          "type": "varchar(20)",
          "primaryKey": false,
          "notNull": true
        },
        "exchange": {
          "name": "exchange",
          "type": "varchar(20)",
          "primaryKey": false,
          "notNull": false
        },
        "updated_at": {
          "name": "updated_at",
          "type": "timestamp",
          "primaryKey": false,
          "notNull": false,
          "default": "now()"
        }
      },
      "indexes": {},
      "foreignKeys": {},
      "compositePrimaryKeys": {},
      "uniqueConstraints": {
        "assets_symbol_unique": {
          "name": "assets_symbol_unique",
          "columns": ["symbol"]
        }
      },
      "policies": {},
      "checkConstraints": {},
      "isRLSEnabled": false
    },
    "public.market_data": {
      "name": "market_data",
      "schema": "",
      "columns": {
        "id": {
          "name": "id",
          "type": "serial",
          "primaryKey": true,
          "notNull": true
        },
        "asset_id": {
          "name": "asset_id",
          "type": "integer",
          "primaryKey": false,
          "notNull": true
        },
        "price_date": {
          "name": "price_date",
          "type": "date",
          "primaryKey": false,
          "notNull": true
        },
        "close_price": {
          "name": "close_price",
          "type": "numeric(20,4)",
          "primaryKey": false,
          "notNull": true
        }
      },
      "indexes": {},
      "foreignKeys": {
        "market_data_asset_id_assets_id_fk": {
          "name": "market_data_asset_id_assets_id_fk",
          "tableFrom": "market_data",
          "tableTo": "assets",
          "columnsFrom": ["asset_id"],
          "columnsTo": ["id"],
          "onUpdate": "no action",
          "onDelete": "no action"
        }
      },
      "compositePrimaryKeys": {},
      "uniqueConstraints": {},
      "policies": {},
      "checkConstraints": {},
      "isRLSEnabled": false
    },
    "public.transactions": {
      "name": "transactions",
      "schema": "",
      "columns": {
        "id": {
          "name": "id",
          "type": "serial",
          "primaryKey": true,
          "notNull": true
        },
        "user_id": {
          "name": "user_id",
          "type": "integer",
          "primaryKey": false,
          "notNull": true
        },
        "asset_id": {
          "name": "asset_id",
          "type": "integer",
          "primaryKey": false,
          "notNull": true
        },
        "type": {
          "name": "type",
          "type": "varchar(10)",
          "primaryKey": false,
          "notNull": true
        },
        "quantity": {
          "name": "quantity",
          "type": "numeric(20,8)",
          "primaryKey": false,
          "notNull": true
        },
        "price_per_unit": {
          "name": "price_per_unit",
          "type": "numeric(20,4)",
          "primaryKey": false,
          "notNull": true
        },
        "total_amount": {
          "name": "total_amount",
          "type": "numeric(20,4)",
          "primaryKey": false,
          "notNull": true
        },
        "executed_at": {
          "name": "executed_at",
          "type": "timestamp",
          "primaryKey": false,
          "notNull": false,
          "default": "now()"
        }
      },
      "indexes": {},
      "foreignKeys": {
        "transactions_user_id_users_id_fk": {
          "name": "transactions_user_id_users_id_fk",
          "tableFrom": "transactions",
          "tableTo": "users",
          "columnsFrom": ["user_id"],
          "columnsTo": ["id"],
          "onUpdate": "no action",
          "onDelete": "no action"
        },
        "transactions_asset_id_assets_id_fk": {
          "name": "transactions_asset_id_assets_id_fk",
          "tableFrom": "transactions",
          "tableTo": "assets",
          "columnsFrom": ["asset_id"],
          "columnsTo": ["id"],
          "onUpdate": "no action",
          "onDelete": "no action"
        }
      },
      "compositePrimaryKeys": {},
      "uniqueConstraints": {},
      "policies": {},
      "checkConstraints": {},
      "isRLSEnabled": false
    },
    "public.user_assets": {
      "name": "user_assets",
      "schema": "",
      "columns": {
        "id": {
          "name": "id",
          "type": "serial",
          "primaryKey": true,
          "notNull": true
        },
        "user_id": {
          "name": "user_id",
          "type": "integer",
          "primaryKey": false,
          "notNull": true
        },
        "asset_id": {
          "name": "asset_id",
          "type": "integer",
          "primaryKey": false,
          "notNull": true
        },
        "quantity": {
          "name": "quantity",
          "type": "numeric(20,8)",
          "primaryKey": false,
          "notNull": true,
          "default": "'0'"
        },
        "avg_cost": {
          "name": "avg_cost",
          "type": "numeric(20,4)",
          "primaryKey": false,
          "notNull": true,
          "default": "'0'"
        },
        "updated_at": {
          "name": "updated_at",
          "type": "timestamp",
          "primaryKey": false,
          "notNull": false,
          "default": "now()"
        }
      },
      "indexes": {
        "user_asset_idx": {
          "name": "user_asset_idx",
          "columns": ["user_id", "asset_id"],
          "isUnique": true
        }
      },
      "foreignKeys": {
        "user_assets_user_id_users_id_fk": {
          "name": "user_assets_user_id_users_id_fk",
          "tableFrom": "user_assets",
          "tableTo": "users",
          "columnsFrom": ["user_id"],
          "columnsTo": ["id"],
          "onUpdate": "no action",
          "onDelete": "no action"
        },
        "user_assets_asset_id_assets_id_fk": {
          "name": "user_assets_asset_id_assets_id_fk",
          "tableFrom": "user_assets",
          "tableTo": "assets",
          "columnsFrom": ["asset_id"],
          "columnsTo": ["id"],
          "onUpdate": "no action",
          "onDelete": "no action"
        }
      },
      "compositePrimaryKeys": {},
      "uniqueConstraints": {},
      "policies": {},
      "checkConstraints": {},
      "isRLSEnabled": false
    },
    "public.portfolio": {
      "name": "portfolio",
      "schema": "",
      "columns": {
        "id": {
          "name": "id",
          "type": "serial",
          "primaryKey": true,
          "notNull": true
        },
        "user_id": {
          "name": "user_id",
          "type": "integer",
          "primaryKey": false,
          "notNull": true
        },
        "symbol": {
          "name": "symbol",
          "type": "varchar(20)",
          "primaryKey": false,
          "notNull": true
        },
        "quantity": {
          "name": "quantity",
          "type": "numeric(15,4)",
          "primaryKey": false,
          "notNull": true
        },
        "average_price": {
          "name": "average_price",
          "type": "numeric(15,4)",
          "primaryKey": false,
          "notNull": true
        },
        "updated_at": {
          "name": "updated_at",
          "type": "timestamp",
          "primaryKey": false,
          "notNull": true,
          "default": "now()"
        }
      },
      "indexes": {},
      "foreignKeys": {
        "portfolio_user_id_users_id_fk": {
          "name": "portfolio_user_id_users_id_fk",
          "tableFrom": "portfolio",
          "tableTo": "users",
          "columnsFrom": ["user_id"],
          "columnsTo": ["id"],
          "onUpdate": "no action",
          "onDelete": "no action"
        }
      },
      "compositePrimaryKeys": {},
      "uniqueConstraints": {},
      "policies": {},
      "checkConstraints": {},
      "isRLSEnabled": false
    },
    "public.orders": {
      "name": "orders",
      "schema": "",
      "columns": {
        "id": {
          "name": "id",
          "type": "serial",
          "primaryKey": true,
          "notNull": true
        },
        "user_id": {
          "name": "user_id",
          "type": "integer",
          "primaryKey": false,
          "notNull": true
        },
        "symbol": {
          "name": "symbol",
          "type": "varchar(20)",
          "primaryKey": false,
          "notNull": true
        },
        "side": {
          "name": "side",
          "type": "varchar(10)",
          "primaryKey": false,
          "notNull": true
        },
        "quantity": {
          "name": "quantity",
          "type": "numeric(15,4)",
          "primaryKey": false,
          "notNull": true
        },
        "price": {
          "name": "price",
          "type": "numeric(15,4)",
          "primaryKey": false,
          "notNull": true
        },
        "total_amount": {
          "name": "total_amount",
          "type": "numeric(15,4)",
          "primaryKey": false,
          "notNull": true
        },
        "status": {
          "name": "status",
          "type": "varchar(20)",
          "primaryKey": false,
          "notNull": false,
          "default": "'COMPLETED'"
        },
        "created_at": {
          "name": "created_at",
          "type": "timestamp",
          "primaryKey": false,
          "notNull": true,
          "default": "now()"
        }
      },
      "indexes": {},
      "foreignKeys": {
        "orders_user_id_users_id_fk": {
          "name": "orders_user_id_users_id_fk",
          "tableFrom": "orders",
          "tableTo": "users",
          "columnsFrom": ["user_id"],
          "columnsTo": ["id"],
          "onUpdate": "no action",
          "onDelete": "no action"
        }
      },
      "compositePrimaryKeys": {},
      "uniqueConstraints": {},
      "policies": {},
      "checkConstraints": {},
      "isRLSEnabled": false
    }
  },
  "enums": {},
  "schemas": {},
  "sequences": {},
  "roles": {},
  "policies": {},
  "views": {},
  "_meta": {
    "columns": {},
    "schemas": {},
    "tables": {}
  }
}